trivoting/__init__.py
trivoting/fractions.py
trivoting/tiebreaking.py
trivoting/utils.py
trivoting/axiomatic/__init__.py
trivoting/axiomatic/justified_representation.py
trivoting/election/__init__.py
trivoting/election/abcvoting.py
trivoting/election/alternative.py
trivoting/election/generate.py
trivoting/election/pabulib.py
trivoting/election/preflib.py
trivoting/election/selection.py
trivoting/election/trichotomous_ballot.py
trivoting/election/trichotomous_profile.py
trivoting/rules/__init__.py
trivoting/rules/chamberlin_courant.py
trivoting/rules/ilp_schemes.py
trivoting/rules/max_net_support.py
trivoting/rules/phragmen.py
trivoting/rules/tax_rules.py
trivoting/rules/thiele.py
trivoting-0.0.7.dist-info/licenses/LICENSE.md
trivoting-0.0.7.dist-info/WHEEL
trivoting-0.0.7.dist-info/METADATA
trivoting-0.0.7.dist-info/RECORD
