Metadata-Version: 2.4
Name: trivoting
Version: 0.0.7
Summary: Library to handle elections with trichotomous preferences
Author-email: Simon Rey <simon.j.rey@proton.me>
Requires-Python: >=3.9
Classifier: Programming Language :: Python :: 3
Classifier: License :: OSI Approved :: GNU General Public License v3 or later (GPLv3+)
Classifier: Operating System :: OS Independent
Classifier: Programming Language :: Python :: 3.9
Classifier: Programming Language :: Python :: 3.10
Classifier: Programming Language :: Python :: 3.11
Classifier: Programming Language :: Python :: 3.12
Classifier: Programming Language :: Python :: 3.13
License-File: LICENSE.md
Requires-Dist: preflibtools>=2.0.33
Requires-Dist: pabutools>=1.2.2
Requires-Dist: abcvoting
Requires-Dist: prefsampling
Requires-Dist: pulp
Requires-Dist: highspy
Requires-Dist: coverage ; extra == "dev"
Requires-Dist: Sphinx ; extra == "dev"
Requires-Dist: sphinx-book-theme ; extra == "dev"
Requires-Dist: sphinxcontrib-napoleon ; extra == "dev"
Requires-Dist: unittest2 ; extra == "dev"
Requires-Dist: sphinx-toolbox ; extra == "dev"
Requires-Dist: pyyaml ; extra == "dev"
Project-URL: Bug Tracker, https://github.com/COMSOC-Community/trivoting/issues
Project-URL: Homepage, https://github.com/COMSOC-Community/trivoting
Provides-Extra: dev
